README
setup.py
pytorchbp/__init__.py
pytorchbp/get_dataset.py
pytorchbp/load_dataset.py
pytorchbp/logger.py
pytorchbp/main.py
pytorchbp.egg-info/PKG-INFO
pytorchbp.egg-info/SOURCES.txt
pytorchbp.egg-info/dependency_links.txt
pytorchbp.egg-info/top_level.txt