Metadata-Version: 1.0
Name: pytorchbp
Version: 0.0.15
Summary: Pytorch Boilerplate Code
Home-page: https://github.com/jprothero/pytorchbp
Author: John Prothero
Author-email: john.s.prothero@gmail.com
License: MIT
Keywords: pytorch boiler plate boilerplate
Platform: UNKNOWN
